[
  {
    "x": 1,
    "y": 133,
    "type": "ending"
  },
  {
    "x": 2,
    "y": 2,
    "type": "ending"
  },
  {
    "x": 3,
    "y": 1,
    "type": "ending"
  },
  {
    "x": 3,
    "y": 66,
    "type": "ending"
  },
  {
    "x": 5,
    "y": 10,
    "type": "ending"
  },
  {
    "x": 5,
    "y": 152,
    "type": "ending"
  },
  {
    "x": 7,
    "y": 158,
    "type": "ending"
  },
  {
    "x": 8,
    "y": 106,
    "type": "ending"
  },
  {
    "x": 8,
    "y": 158,
    "type": "ending"
  },
  {
    "x": 9,
    "y": 100,
    "type": "ending"
  },
  {
    "x": 10,
    "y": 6,
    "type": "ending"
  },
  {
    "x": 15,
    "y": 19,
    "type": "ending"
  },
  {
    "x": 15,
    "y": 96,
    "type": "ending"
  },
  {
    "x": 16,
    "y": 1,
    "type": "ending"
  },
  {
    "x": 16,
    "y": 92,
    "type": "ending"
  },
  {
    "x": 18,
    "y": 141,
    "type": "ending"
  },
  {
    "x": 18,
    "y": 158,
    "type": "ending"
  },
  {
    "x": 19,
    "y": 17,
    "type": "ending"
  },
  {
    "x": 20,
    "y": 112,
    "type": "ending"
  },
  {
    "x": 21,
    "y": 146,
    "type": "ending"
  },
  {
    "x": 22,
    "y": 38,
    "type": "ending"
  },
  {
    "x": 22,
    "y": 118,
    "type": "ending"
  },
  {
    "x": 23,
    "y": 89,
    "type": "ending"
  },
  {
    "x": 24,
    "y": 32,
    "type": "ending"
  },
  {
    "x": 24,
    "y": 33,
    "type": "ending"
  },
  {
    "x": 25,
    "y": 81,
    "type": "ending"
  },
  {
    "x": 26,
    "y": 107,
    "type": "ending"
  },
  {
    "x": 28,
    "y": 101,
    "type": "ending"
  },
  {
    "x": 28,
    "y": 104,
    "type": "ending"
  },
  {
    "x": 28,
    "y": 106,
    "type": "bifurcation"
  },
  {
    "x": 28,
    "y": 107,
    "type": "bifurcation"
  },
  {
    "x": 28,
    "y": 113,
    "type": "ending"
  },
  {
    "x": 28,
    "y": 116,
    "type": "ending"
  },
  {
    "x": 28,
    "y": 121,
    "type": "ending"
  },
  {
    "x": 29,
    "y": 28,
    "type": "ending"
  },
  {
    "x": 30,
    "y": 7,
    "type": "ending"
  },
  {
    "x": 30,
    "y": 129,
    "type": "ending"
  },
  {
    "x": 31,
    "y": 88,
    "type": "ending"
  },
  {
    "x": 32,
    "y": 135,
    "type": "ending"
  },
  {
    "x": 33,
    "y": 102,
    "type": "ending"
  },
  {
    "x": 33,
    "y": 104,
    "type": "ending"
  },
  {
    "x": 34,
    "y": 6,
    "type": "ending"
  },
  {
    "x": 34,
    "y": 81,
    "type": "ending"
  },
  {
    "x": 34,
    "y": 109,
    "type": "ending"
  },
  {
    "x": 35,
    "y": 14,
    "type": "ending"
  },
  {
    "x": 35,
    "y": 114,
    "type": "ending"
  },
  {
    "x": 35,
    "y": 124,
    "type": "ending"
  },
  {
    "x": 36,
    "y": 46,
    "type": "ending"
  },
  {
    "x": 36,
    "y": 99,
    "type": "ending"
  },
  {
    "x": 36,
    "y": 117,
    "type": "ending"
  },
  {
    "x": 37,
    "y": 21,
    "type": "ending"
  },
  {
    "x": 37,
    "y": 128,
    "type": "ending"
  },
  {
    "x": 38,
    "y": 42,
    "type": "ending"
  },
  {
    "x": 38,
    "y": 128,
    "type": "ending"
  },
  {
    "x": 39,
    "y": 9,
    "type": "ending"
  },
  {
    "x": 40,
    "y": 132,
    "type": "ending"
  },
  {
    "x": 40,
    "y": 145,
    "type": "ending"
  },
  {
    "x": 41,
    "y": 18,
    "type": "ending"
  },
  {
    "x": 43,
    "y": 122,
    "type": "ending"
  },
  {
    "x": 44,
    "y": 36,
    "type": "ending"
  },
  {
    "x": 44,
    "y": 58,
    "type": "ending"
  },
  {
    "x": 44,
    "y": 81,
    "type": "ending"
  },
  {
    "x": 46,
    "y": 34,
    "type": "ending"
  },
  {
    "x": 46,
    "y": 127,
    "type": "ending"
  },
  {
    "x": 46,
    "y": 150,
    "type": "ending"
  },
  {
    "x": 47,
    "y": 22,
    "type": "ending"
  },
  {
    "x": 47,
    "y": 126,
    "type": "ending"
  },
  {
    "x": 47,
    "y": 158,
    "type": "ending"
  },
  {
    "x": 48,
    "y": 132,
    "type": "ending"
  },
  {
    "x": 50,
    "y": 43,
    "type": "bifurcation"
  },
  {
    "x": 50,
    "y": 56,
    "type": "ending"
  },
  {
    "x": 50,
    "y": 65,
    "type": "ending"
  },
  {
    "x": 50,
    "y": 75,
    "type": "ending"
  },
  {
    "x": 50,
    "y": 97,
    "type": "ending"
  },
  {
    "x": 50,
    "y": 115,
    "type": "ending"
  },
  {
    "x": 50,
    "y": 143,
    "type": "ending"
  },
  {
    "x": 51,
    "y": 42,
    "type": "bifurcation"
  },
  {
    "x": 51,
    "y": 43,
    "type": "bifurcation"
  },
  {
    "x": 51,
    "y": 62,
    "type": "ending"
  },
  {
    "x": 52,
    "y": 18,
    "type": "ending"
  },
  {
    "x": 52,
    "y": 44,
    "type": "ending"
  },
  {
    "x": 52,
    "y": 84,
    "type": "ending"
  },
  {
    "x": 52,
    "y": 110,
    "type": "ending"
  },
  {
    "x": 53,
    "y": 121,
    "type": "ending"
  },
  {
    "x": 55,
    "y": 102,
    "type": "ending"
  },
  {
    "x": 56,
    "y": 79,
    "type": "ending"
  },
  {
    "x": 57,
    "y": 146,
    "type": "ending"
  },
  {
    "x": 58,
    "y": 42,
    "type": "ending"
  },
  {
    "x": 58,
    "y": 98,
    "type": "ending"
  },
  {
    "x": 59,
    "y": 107,
    "type": "bifurcation"
  },
  {
    "x": 59,
    "y": 124,
    "type": "ending"
  },
  {
    "x": 60,
    "y": 65,
    "type": "ending"
  },
  {
    "x": 60,
    "y": 98,
    "type": "bifurcation"
  },
  {
    "x": 60,
    "y": 107,
    "type": "bifurcation"
  },
  {
    "x": 60,
    "y": 132,
    "type": "ending"
  },
  {
    "x": 61,
    "y": 97,
    "type": "bifurcation"
  },
  {
    "x": 61,
    "y": 98,
    "type": "bifurcation"
  },
  {
    "x": 61,
    "y": 139,
    "type": "ending"
  },
  {
    "x": 62,
    "y": 126,
    "type": "ending"
  },
  {
    "x": 63,
    "y": 3,
    "type": "bifurcation"
  },
  {
    "x": 63,
    "y": 45,
    "type": "ending"
  },
  {
    "x": 64,
    "y": 3,
    "type": "bifurcation"
  },
  {
    "x": 64,
    "y": 5,
    "type": "ending"
  },
  {
    "x": 64,
    "y": 21,
    "type": "ending"
  },
  {
    "x": 65,
    "y": 3,
    "type": "bifurcation"
  },
  {
    "x": 66,
    "y": 28,
    "type": "ending"
  },
  {
    "x": 66,
    "y": 62,
    "type": "ending"
  },
  {
    "x": 67,
    "y": 21,
    "type": "ending"
  },
  {
    "x": 67,
    "y": 37,
    "type": "ending"
  },
  {
    "x": 67,
    "y": 112,
    "type": "ending"
  },
  {
    "x": 67,
    "y": 140,
    "type": "ending"
  },
  {
    "x": 68,
    "y": 45,
    "type": "ending"
  },
  {
    "x": 68,
    "y": 69,
    "type": "ending"
  },
  {
    "x": 68,
    "y": 126,
    "type": "ending"
  },
  {
    "x": 68,
    "y": 158,
    "type": "ending"
  },
  {
    "x": 69,
    "y": 27,
    "type": "ending"
  },
  {
    "x": 69,
    "y": 141,
    "type": "ending"
  },
  {
    "x": 70,
    "y": 149,
    "type": "ending"
  },
  {
    "x": 72,
    "y": 33,
    "type": "ending"
  },
  {
    "x": 72,
    "y": 49,
    "type": "ending"
  },
  {
    "x": 72,
    "y": 110,
    "type": "ending"
  },
  {
    "x": 73,
    "y": 1,
    "type": "ending"
  },
  {
    "x": 73,
    "y": 67,
    "type": "ending"
  },
  {
    "x": 73,
    "y": 156,
    "type": "ending"
  },
  {
    "x": 74,
    "y": 76,
    "type": "bifurcation"
  },
  {
    "x": 74,
    "y": 126,
    "type": "ending"
  },
  {
    "x": 74,
    "y": 142,
    "type": "ending"
  },
  {
    "x": 74,
    "y": 155,
    "type": "ending"
  },
  {
    "x": 75,
    "y": 75,
    "type": "bifurcation"
  },
  {
    "x": 75,
    "y": 76,
    "type": "bifurcation"
  },
  {
    "x": 75,
    "y": 96,
    "type": "ending"
  },
  {
    "x": 76,
    "y": 65,
    "type": "ending"
  },
  {
    "x": 76,
    "y": 73,
    "type": "ending"
  },
  {
    "x": 77,
    "y": 48,
    "type": "ending"
  },
  {
    "x": 77,
    "y": 110,
    "type": "ending"
  },
  {
    "x": 78,
    "y": 93,
    "type": "ending"
  },
  {
    "x": 78,
    "y": 102,
    "type": "ending"
  },
  {
    "x": 78,
    "y": 148,
    "type": "ending"
  },
  {
    "x": 79,
    "y": 108,
    "type": "ending"
  },
  {
    "x": 80,
    "y": 140,
    "type": "ending"
  },
  {
    "x": 81,
    "y": 62,
    "type": "ending"
  },
  {
    "x": 81,
    "y": 84,
    "type": "ending"
  },
  {
    "x": 81,
    "y": 125,
    "type": "ending"
  },
  {
    "x": 81,
    "y": 132,
    "type": "bifurcation"
  },
  {
    "x": 82,
    "y": 92,
    "type": "bifurcation"
  },
  {
    "x": 82,
    "y": 99,
    "type": "ending"
  },
  {
    "x": 82,
    "y": 132,
    "type": "bifurcation"
  },
  {
    "x": 82,
    "y": 133,
    "type": "bifurcation"
  },
  {
    "x": 82,
    "y": 134,
    "type": "ending"
  },
  {
    "x": 82,
    "y": 154,
    "type": "ending"
  },
  {
    "x": 82,
    "y": 155,
    "type": "ending"
  },
  {
    "x": 83,
    "y": 69,
    "type": "ending"
  },
  {
    "x": 83,
    "y": 92,
    "type": "bifurcation"
  },
  {
    "x": 83,
    "y": 94,
    "type": "ending"
  },
  {
    "x": 83,
    "y": 100,
    "type": "ending"
  },
  {
    "x": 84,
    "y": 92,
    "type": "bifurcation"
  },
  {
    "x": 85,
    "y": 147,
    "type": "ending"
  },
  {
    "x": 86,
    "y": 83,
    "type": "ending"
  },
  {
    "x": 86,
    "y": 138,
    "type": "ending"
  },
  {
    "x": 88,
    "y": 105,
    "type": "ending"
  },
  {
    "x": 90,
    "y": 64,
    "type": "ending"
  },
  {
    "x": 91,
    "y": 96,
    "type": "ending"
  },
  {
    "x": 91,
    "y": 105,
    "type": "ending"
  },
  {
    "x": 91,
    "y": 145,
    "type": "ending"
  },
  {
    "x": 93,
    "y": 145,
    "type": "ending"
  },
  {
    "x": 94,
    "y": 153,
    "type": "ending"
  },
  {
    "x": 95,
    "y": 152,
    "type": "ending"
  },
  {
    "x": 96,
    "y": 27,
    "type": "ending"
  },
  {
    "x": 96,
    "y": 102,
    "type": "ending"
  },
  {
    "x": 97,
    "y": 93,
    "type": "ending"
  },
  {
    "x": 98,
    "y": 109,
    "type": "ending"
  },
  {
    "x": 100,
    "y": 25,
    "type": "ending"
  },
  {
    "x": 100,
    "y": 126,
    "type": "ending"
  },
  {
    "x": 102,
    "y": 68,
    "type": "ending"
  },
  {
    "x": 102,
    "y": 94,
    "type": "ending"
  },
  {
    "x": 104,
    "y": 110,
    "type": "ending"
  },
  {
    "x": 104,
    "y": 135,
    "type": "ending"
  },
  {
    "x": 107,
    "y": 42,
    "type": "ending"
  },
  {
    "x": 107,
    "y": 119,
    "type": "ending"
  },
  {
    "x": 109,
    "y": 64,
    "type": "ending"
  },
  {
    "x": 110,
    "y": 13,
    "type": "ending"
  },
  {
    "x": 110,
    "y": 28,
    "type": "ending"
  },
  {
    "x": 111,
    "y": 124,
    "type": "ending"
  },
  {
    "x": 112,
    "y": 116,
    "type": "ending"
  },
  {
    "x": 112,
    "y": 126,
    "type": "ending"
  },
  {
    "x": 113,
    "y": 15,
    "type": "ending"
  },
  {
    "x": 115,
    "y": 57,
    "type": "ending"
  },
  {
    "x": 115,
    "y": 123,
    "type": "ending"
  },
  {
    "x": 116,
    "y": 88,
    "type": "ending"
  },
  {
    "x": 118,
    "y": 43,
    "type": "ending"
  },
  {
    "x": 118,
    "y": 49,
    "type": "ending"
  },
  {
    "x": 118,
    "y": 92,
    "type": "bifurcation"
  },
  {
    "x": 119,
    "y": 91,
    "type": "bifurcation"
  },
  {
    "x": 119,
    "y": 92,
    "type": "bifurcation"
  },
  {
    "x": 119,
    "y": 113,
    "type": "ending"
  },
  {
    "x": 120,
    "y": 122,
    "type": "ending"
  },
  {
    "x": 122,
    "y": 93,
    "type": "ending"
  },
  {
    "x": 123,
    "y": 56,
    "type": "ending"
  },
  {
    "x": 124,
    "y": 110,
    "type": "ending"
  },
  {
    "x": 125,
    "y": 49,
    "type": "ending"
  },
  {
    "x": 125,
    "y": 109,
    "type": "bifurcation"
  },
  {
    "x": 126,
    "y": 6,
    "type": "ending"
  },
  {
    "x": 126,
    "y": 29,
    "type": "ending"
  },
  {
    "x": 126,
    "y": 49,
    "type": "ending"
  },
  {
    "x": 126,
    "y": 85,
    "type": "ending"
  },
  {
    "x": 126,
    "y": 107,
    "type": "ending"
  },
  {
    "x": 127,
    "y": 62,
    "type": "ending"
  },
  {
    "x": 127,
    "y": 122,
    "type": "ending"
  },
  {
    "x": 128,
    "y": 92,
    "type": "ending"
  },
  {
    "x": 128,
    "y": 121,
    "type": "ending"
  },
  {
    "x": 131,
    "y": 44,
    "type": "ending"
  },
  {
    "x": 131,
    "y": 101,
    "type": "ending"
  },
  {
    "x": 132,
    "y": 6,
    "type": "ending"
  },
  {
    "x": 132,
    "y": 7,
    "type": "ending"
  },
  {
    "x": 133,
    "y": 29,
    "type": "ending"
  },
  {
    "x": 133,
    "y": 61,
    "type": "ending"
  },
  {
    "x": 135,
    "y": 103,
    "type": "ending"
  },
  {
    "x": 136,
    "y": 37,
    "type": "ending"
  },
  {
    "x": 136,
    "y": 102,
    "type": "ending"
  },
  {
    "x": 137,
    "y": 42,
    "type": "ending"
  },
  {
    "x": 139,
    "y": 92,
    "type": "ending"
  },
  {
    "x": 140,
    "y": 6,
    "type": "ending"
  },
  {
    "x": 141,
    "y": 103,
    "type": "ending"
  },
  {
    "x": 141,
    "y": 108,
    "type": "ending"
  },
  {
    "x": 142,
    "y": 35,
    "type": "ending"
  },
  {
    "x": 142,
    "y": 110,
    "type": "ending"
  },
  {
    "x": 143,
    "y": 21,
    "type": "ending"
  },
  {
    "x": 143,
    "y": 102,
    "type": "ending"
  },
  {
    "x": 144,
    "y": 69,
    "type": "ending"
  },
  {
    "x": 145,
    "y": 36,
    "type": "ending"
  },
  {
    "x": 146,
    "y": 75,
    "type": "ending"
  },
  {
    "x": 150,
    "y": 37,
    "type": "ending"
  },
  {
    "x": 150,
    "y": 72,
    "type": "ending"
  },
  {
    "x": 150,
    "y": 95,
    "type": "ending"
  },
  {
    "x": 150,
    "y": 97,
    "type": "ending"
  },
  {
    "x": 151,
    "y": 24,
    "type": "ending"
  },
  {
    "x": 151,
    "y": 70,
    "type": "ending"
  },
  {
    "x": 152,
    "y": 76,
    "type": "ending"
  },
  {
    "x": 152,
    "y": 78,
    "type": "ending"
  },
  {
    "x": 152,
    "y": 85,
    "type": "ending"
  },
  {
    "x": 154,
    "y": 39,
    "type": "ending"
  },
  {
    "x": 157,
    "y": 26,
    "type": "ending"
  },
  {
    "x": 157,
    "y": 56,
    "type": "ending"
  },
  {
    "x": 157,
    "y": 73,
    "type": "ending"
  },
  {
    "x": 158,
    "y": 4,
    "type": "ending"
  },
  {
    "x": 158,
    "y": 10,
    "type": "ending"
  },
  {
    "x": 158,
    "y": 17,
    "type": "ending"
  },
  {
    "x": 158,
    "y": 32,
    "type": "ending"
  },
  {
    "x": 158,
    "y": 50,
    "type": "ending"
  },
  {
    "x": 158,
    "y": 66,
    "type": "ending"
  },
  {
    "x": 158,
    "y": 71,
    "type": "ending"
  },
  {
    "x": 158,
    "y": 81,
    "type": "ending"
  },
  {
    "x": 158,
    "y": 82,
    "type": "ending"
  }
]